pylarky/README.md
pylarky/__init__.py
pylarky/eval/__init__.py
pylarky/eval/evaluator.py
pylarky/eval/http_evaluator.py
pylarky/larky-runner
pylarky/model/__init__.py
pylarky/model/http_message.py
pylarky-0.12.21.dist-info/LICENSE
pylarky-0.12.21.dist-info/METADATA
pylarky-0.12.21.dist-info/WHEEL
pylarky-0.12.21.dist-info/RECORD
