Metadata-Version: 2.1
Name: pylarky
Version: 0.12.21
Summary: Python wrapper for starlarky runner
License: Apache License v2.0
Author: Very Good Security
Requires-Python: >=3.8,<4.0
Classifier: License :: Other/Proprietary License
Classifier: Programming Language :: Python :: 3
Classifier: Programming Language :: Python :: 3.8
Classifier: Programming Language :: Python :: 3.9
Classifier: Programming Language :: Python :: 3.10
Classifier: Programming Language :: Python :: 3.11
